jfx_bridge_ida/__init__.py
jfx_bridge_ida/install_server.py
jfx_bridge_ida/jfx_bridge_ida.py
jfx_bridge_ida/test_jfx_bridge_ida.py
jfx_bridge_ida/test_module.py
jfx_bridge_ida/server/__init__.py
jfx_bridge_ida/server/jfx_bridge_ida_port.py
jfx_bridge_ida/server/jfx_bridge_ida_server.py
jfx_bridge_ida/server/jfx_bridge_ida_server_shutdown.py
jfx_bridge_ida-0.2.1.dist-info/LICENSE
jfx_bridge_ida-0.2.1.dist-info/METADATA
jfx_bridge_ida-0.2.1.dist-info/WHEEL
jfx_bridge_ida-0.2.1.dist-info/top_level.txt
jfx_bridge_ida-0.2.1.dist-info/RECORD
