Metadata-Version: 2.1
Name: jfx-bridge-ida
Version: 0.2.1
Summary: RPC bridge from Python to IDA Python interpreter
Home-page: https://github.com/justfoxing/jfx_bridge_ida
Author: justfoxing
Author-email: justfoxingprojects@gmail.com
License: UNKNOWN
Platform: UNKNOWN
Classifier: Programming Language :: Python
Classifier: License :: OSI Approved :: MIT License
Classifier: Operating System :: OS Independent
Requires-Dist: jfx-bridge (>=0.8.0)
